setup.py
arcanelab/__init__.py
arcanelab/ouroboros/__init__.py
arcanelab/ouroboros/exceptions.py
arcanelab/ouroboros/executors.py
arcanelab/ouroboros/fields.py
arcanelab/ouroboros/models.py
arcanelab/ouroboros/support.py
arcanelab/ouroboros/locale/en/LC_MESSAGES/django.mo
arcanelab/ouroboros/locale/en/LC_MESSAGES/django.po
arcanelab/ouroboros/locale/es/LC_MESSAGES/django.mo
arcanelab/ouroboros/locale/es/LC_MESSAGES/django.po
arcanelab/ouroboros/migrations/0001_initial.py
arcanelab/ouroboros/migrations/0002_courseinstancelog.py
arcanelab/ouroboros/migrations/0003_auto_20160809_0341.py
arcanelab/ouroboros/migrations/0004_auto_20160814_2347.py
arcanelab/ouroboros/migrations/0005_auto_20160926_0057.py
arcanelab/ouroboros/migrations/__init__.py
arcanelab_ouroboros.egg-info/PKG-INFO
arcanelab_ouroboros.egg-info/SOURCES.txt
arcanelab_ouroboros.egg-info/dependency_links.txt
arcanelab_ouroboros.egg-info/namespace_packages.txt
arcanelab_ouroboros.egg-info/requires.txt
arcanelab_ouroboros.egg-info/top_level.txt