Metadata-Version: 1.0
Name: arcanelab-ouroboros
Version: 0.0.1
Summary: Workflow library for Django
Home-page: https://github.com/luismasuelli/arcanelab-ouroboros
Author: Luis y Anita
Author-email: luismasuelli@hotmail.com
License: LGPL
Platform: UNKNOWN
